README.rst
fsredis.py
setup.py
test_fsredis.py
fsredis.egg-info/PKG-INFO
fsredis.egg-info/SOURCES.txt
fsredis.egg-info/dependency_links.txt
fsredis.egg-info/top_level.txt