Metadata-Version: 1.1
Name: fsredis
Version: 0.4
Summary: fsredis: in-process redis api, persisting to file system.
Home-page: http://github.com/hpk42/fsredis
Author: holger krekel
Author-email: holger at merlinux.eu
License: MIT license
Platform: unix
Platform: linux
Platform: osx
Platform: cygwin
Platform: win32
Classifier: Development Status :: 3 - Alpha
Classifier: Intended Audience :: Developers
Classifier: License :: OSI Approved :: MIT License
Classifier: Operating System :: POSIX
Classifier: Operating System :: Microsoft :: Windows
Classifier: Operating System :: MacOS :: MacOS X
Classifier: Topic :: Utilities
Classifier: Intended Audience :: Developers
Classifier: Programming Language :: Python
